cjrh_math.py
cjrh_math-2017.11.1.dist-info/LICENSE
cjrh_math-2017.11.1.dist-info/WHEEL
cjrh_math-2017.11.1.dist-info/METADATA
cjrh_math-2017.11.1.dist-info/RECORD
