Metadata-Version: 1.2
Name: cjrh_math
Version: 2017.11.1
Summary: Maths functions
Home-page: https://github.com/cjrh/cjrh_math
License: UNKNOWN
Author: Caleb Hattingh
Author-email: caleb.hattingh@gmail.com
Classifier: License :: OSI Approved :: Apache Software License
Classifier: Natural Language :: English
Classifier: Programming Language :: Python
Classifier: Programming Language :: Python :: 3.5
Classifier: Programming Language :: Python :: 3.6
Classifier: Operating System :: OS Independent
